__init__.py
ailite/__init__.py
ailite/features/__init__.py
ailite/features/ailite_ollama.py
ailite/features/inference_gradio.py
ailite/hf_official_api/__init__.py
ailite/hf_official_api/main.py
ailite/main/__init__.py
ailite/main/_ailite.py
ailite/main/_ailite_api.py
ailite/main/_ailite_streamlit.py
ailite/main/_model/__init__.py
ailite/main/_model/_api/__init__.py
ailite/main/_model/_api/_chatbot.py
ailite/main/_model/_api/_client.py
ailite/main/_model/_api/_models.py
ailite/main/_model/_api/_tool_calling.py
ailite/main/_model/_api/resources/__init__.py
ailite/main/_model/_api/resources/messages.py
ailite/main/_model/_api/types/__init__.py
ailite/main/_model/_api/types/_message.py
ailite/main/_model/_api/types/_model_types.py
ailite/main/_model/_api/types/content_block.py
ailite/main/_model/_api/types/text_block.py
ailite/main/_model/_api/types/text_block_param.py
ailite/main/_model/_api/types/tool_param.py
ailite/main/_model/_api/types/tool_result_block_param.py
ailite/main/_model/_api/types/tool_use_block.py
ailite/main/_model/_api/types/tool_use_block_param.py
ailite/main/_model/_api/types/usage.py
ailite/main/_model/_base/__init__.py
ailite/main/_model/_base/_base_huggy_chat.py
ailite/main/_model/_base/_base_llm.py
ailite/main/_model/_base/_base_login.py
ailite/main/_model/_base/_hf_chatbot_custom.py
ailite/main/_model/_utils/__init__.py
ailite/main/_model/_utils/_const.py
ailite/main/_model/_utils/_print_text.py
ailite/prompts/__init__.py
ailite/prompts/prompts.py
ailite_legacy-0.0.1.dist-info/LICENSE
ailite_legacy-0.0.1.dist-info/METADATA
ailite_legacy-0.0.1.dist-info/WHEEL
ailite_legacy-0.0.1.dist-info/top_level.txt
ailite_legacy-0.0.1.dist-info/RECORD
