Metadata-Version: 2.1
Name: ailite_legacy
Version: 0.0.1
Summary: HuggingFace Commercial Model Free API 
Author-email: Your Name <your.email@example.com>
Project-URL: Homepage, https://github.com/yourusername/pyopengenai
Project-URL: Bug Tracker, https://github.com/yourusername/pyopengenai/issues
Classifier: Programming Language :: Python :: 3
Classifier: License :: OSI Approved :: MIT License
Classifier: Operating System :: OS Independent
Requires-Python: >=3.7
License-File: LICENSE
Requires-Dist: parselite
Requires-Dist: searchlite
Requires-Dist: langchain_core
Requires-Dist: uvicorn
Requires-Dist: fastapi
Requires-Dist: hugpi
Requires-Dist: hugchat
Requires-Dist: gradio-client
